odoo8_addon_sale_department-8.0.1.0.0-py2.7-nspkg.pth
odoo8_addon_sale_department-8.0.1.0.0.dist-info/top_level.txt
odoo8_addon_sale_department-8.0.1.0.0.dist-info/WHEEL
odoo8_addon_sale_department-8.0.1.0.0.dist-info/RECORD
odoo8_addon_sale_department-8.0.1.0.0.dist-info/metadata.json
odoo8_addon_sale_department-8.0.1.0.0.dist-info/DESCRIPTION.rst
odoo8_addon_sale_department-8.0.1.0.0.dist-info/METADATA
odoo8_addon_sale_department-8.0.1.0.0.dist-info/namespace_packages.txt
odoo_addons/sale_department/__openerp__.py
odoo_addons/sale_department/sale.py
odoo_addons/sale_department/sale_view.xml
odoo_addons/sale_department/__init__.py
odoo_addons/sale_department/LICENSE
odoo_addons/sale_department/i18n/sale_department.pot
odoo_addons/sale_department/i18n/es.po
odoo_addons/sale_department/i18n/bg.po
